gempaterkini/__init__.py
latestearthquake_indonesia.1-0.5.dist-info/LICENSE
latestearthquake_indonesia.1-0.5.dist-info/METADATA
latestearthquake_indonesia.1-0.5.dist-info/WHEEL
latestearthquake_indonesia.1-0.5.dist-info/top_level.txt
latestearthquake_indonesia.1-0.5.dist-info/RECORD
