Metadata-Version: 2.1
Name: latestearthquake-indonesia.1
Version: 0.5
Summary: This package will get the latest earthquake from BMKG | Indonesian Agency for Meteorological, Climatological and Geophysics 
Home-page: https://github.com/WildanAruman/deteksi-gempa-terkini
Author: Wildan Aruman
Author-email: wildan.aruman90@gmail.com
License: UNKNOWN
Project-URL: Bug Tracker, https://github.com/WildanAruman/deteksi-gempa-terkini
Platform: UNKNOWN
Classifier: Programming Language :: Python :: 3
Classifier: License :: OSI Approved :: MIT License
Classifier: Operating System :: OS Independent
Classifier: Development Status :: 5 - Production/Stable
Requires-Python: >=3.6
License-File: LICENSE
